class27/__init__.py
class27/zhulianglin.py
class27/pic/代广涵/微信图片_20251204105356_2237_25.jpg
class27/pic/代广涵/微信图片_20251204110631_2293_25.jpg
class27/pic/代广涵/微信图片_20251204110712_2296_25.jpg
class27/pic/代广涵/微信图片_20251204113411_2377_25.jpg
class27/pic/侯凤云/微信图片_20251204113309_2374_25.jpg
class27/pic/冯雨晨/mmexport1758145911869.jpg
class27/pic/冯雨晨/微信图片_20251204105335_2236_25.jpg
class27/pic/冯雨晨/微信图片_20251204112341_2352_25.jpg
class27/pic/冯雨晨/微信图片_20251204112831_2364_25.jpg
class27/pic/刘梓航/微信图片_20251204105434_2239_25.jpg
class27/pic/刘珂奇/微信图片_20251204112009_2339_25.jpg
class27/pic/刘珂奇/微信图片_20251204145311_2436_25.jpg
class27/pic/合影/IMG_20250623_005417.jpg
class27/pic/合影/IMG_20250623_005459.jpg
class27/pic/合影/mmexport1750615564696.jpg
class27/pic/合影/mmexport1751060375586.jpg
class27/pic/合影/mmexport1751060487308(1).jpg
class27/pic/合影/mmexport1751060498652(1).jpg
class27/pic/合影/mmexport1757688932880(1).jpg
class27/pic/合影/mmexport1758145866357.jpg
class27/pic/合影/mmexport1758442007687.jpg
class27/pic/合影/mmexport1759421587794(1).jpg
class27/pic/合影/mmexport1761023172007.jpg
class27/pic/合影/mmexport1761023187922(1).jpg
class27/pic/合影/mmexport1761023201741.jpg
class27/pic/合影/mmexport1761023539485.jpg
class27/pic/合影/mmexport1761023585275.jpg
class27/pic/合影/mmexport1761023683863.jpg
class27/pic/合影/mmexport1761366708848.jpg
class27/pic/合影/mmexport1762399382906.jpg
class27/pic/合影/mmexport1762399388102.jpg
class27/pic/合影/mmexport1763464189845(1).jpg
class27/pic/合影/微信图片_20251203190715_2085_25.jpg
class27/pic/合影/微信图片_20251203191114_2105_25.jpg
class27/pic/合影/微信图片_20251203191312_2109_25.jpg
class27/pic/合影/微信图片_20251203191349_2111_25.jpg
class27/pic/合影/微信图片_20251203191350_2112_25.jpg
class27/pic/合影/微信图片_20251203191544_2113_25.jpg
class27/pic/合影/微信图片_20251203191545_2114_25.jpg
class27/pic/合影/微信图片_20251203191546_2115_25.jpg
class27/pic/合影/微信图片_20251203191547_2116_25.jpg
class27/pic/合影/微信图片_20251203191824_2122_25.jpg
class27/pic/合影/微信图片_20251203191851_2123_25.jpg
class27-2.0.3.dist-info/METADATA
class27-2.0.3.dist-info/WHEEL
class27-2.0.3.dist-info/licenses/LICENSE
class27-2.0.3.dist-info/RECORD
