Metadata-Version: 2.4
Name: class27
Version: 2.0.3
Summary: 关于25届萧县实验27班
Project-URL: Homepage, https://github.com/youxingliang/class27
Author-email: youxingliang <yxl070625@qq.com>
License-File: LICENSE
Classifier: License :: OSI Approved :: MIT License
Classifier: Operating System :: OS Independent
Classifier: Programming Language :: Python :: 3
Classifier: Programming Language :: Python :: 3.8
Classifier: Programming Language :: Python :: 3.9
Classifier: Programming Language :: Python :: 3.10
Classifier: Programming Language :: Python :: 3.11
Classifier: Programming Language :: Python :: 3.12
Classifier: Topic :: Utilities
Requires-Python: >=3.8
